hashbox/__init__.py
hashbox/api.md
hashbox/constants.py
hashbox/exceptions.py
hashbox/frozen/__init__.py
hashbox/frozen/frozen_attr.py
hashbox/frozen/how_it_works.md
hashbox/frozen/main.py
hashbox/frozen/utils.py
hashbox/init_helpers.py
hashbox/mutable/__init__.py
hashbox/mutable/how_it_works.md
hashbox/mutable/main.py
hashbox/mutable/mutable_attr.py
hashbox/perf.py
hashbox/utils.py
hashbox-0.5.1.dist-info/LICENSE
hashbox-0.5.1.dist-info/WHEEL
hashbox-0.5.1.dist-info/METADATA
hashbox-0.5.1.dist-info/RECORD
