Metadata-Version: 2.1
Name: hashbox
Version: 0.5.1
Summary: Find Python objects by exact match on their attributes.
Home-page: https://github.com/manimino/hashbox/
License: MIT
Author: Theo Walker
Author-email: theo.ca.walker@gmail.com
Requires-Python: >=3.7,<4.0
Classifier: License :: OSI Approved :: MIT License
Classifier: Programming Language :: Python :: 3
Classifier: Programming Language :: Python :: 3.10
Classifier: Programming Language :: Python :: 3.7
Classifier: Programming Language :: Python :: 3.8
Classifier: Programming Language :: Python :: 3.9
Requires-Dist: cykhash (>=2.0.0,<3.0.0)
Requires-Dist: numpy (>=1.14,<2.0)
Requires-Dist: sortednp (>=0.4.0,<0.5.0)
Project-URL: Documentation, https://pypi.org/project/hashbox/
Project-URL: Repository, https://github.com/manimino/hashbox/
